{
  "updated_at": "2026-04-23T10:09:56Z",
  "rates": {
    "USD_NGN": {
      "foreign": "USD",
      "local": "NGN",
      "flag": "\ud83c\uddf3\ud83c\uddec",
      "country": "Nigeria",
      "sym": "\u20a6",
      "parallel_label": "Parallel market",
      "parallel_rate": 1373.04,
      "cbn_rate": 1349.0,
      "spread": 24.04,
      "spread_pct": 1.78,
      "fetched_at": "2026-04-23 10:09"
    },
    "GBP_NGN": {
      "foreign": "GBP",
      "local": "NGN",
      "flag": "\ud83c\uddf3\ud83c\uddec",
      "country": "Nigeria",
      "sym": "\u20a6",
      "parallel_label": "Parallel market",
      "parallel_rate": 1843.95,
      "cbn_rate": 1827.89,
      "spread": 16.06,
      "spread_pct": 0.88,
      "fetched_at": "2026-04-23 10:09"
    },
    "EUR_NGN": {
      "foreign": "EUR",
      "local": "NGN",
      "flag": "\ud83c\uddf3\ud83c\uddec",
      "country": "Nigeria",
      "sym": "\u20a6",
      "parallel_label": "Parallel market",
      "parallel_rate": 1596.95,
      "cbn_rate": 1588.24,
      "spread": 8.71,
      "spread_pct": 0.55,
      "fetched_at": "2026-04-23 10:09"
    }
  }
}